meiya_ai/__init__.py
meiya_ai/main.py
meiya_ai/filter/__init__.py
meiya_ai/filter/utils.py
meiya_ai/filter/hashlib_filter/__init__.py
meiya_ai/filter/hashlib_filter/filter_hashlib.py
meiya_ai/filter/pandas_filter/__init__.py
meiya_ai/filter/pandas_filter/filter_pandas.py
meiya_ai/generate/__init__.py
meiya_ai-0.0.7.dist-info/METADATA
meiya_ai-0.0.7.dist-info/WHEEL
meiya_ai-0.0.7.dist-info/entry_points.txt
meiya_ai-0.0.7.dist-info/top_level.txt
meiya_ai-0.0.7.dist-info/RECORD
