Metadata-Version: 2.1
Name: meiya_ai
Version: 0.0.7
Summary: meiya pico ai tools for process data 
Home-page: https://github.com/amanyara
Author: yuhan zhangyh
Author-email: yhanzh0608@gmail.com
License: MIT
Keywords: python,data  process,meiyapico ai
Classifier: Development Status :: 3 - Alpha
Classifier: Intended Audience :: Developers
Classifier: Programming Language :: Python :: 3
Classifier: Operating System :: POSIX :: Linux
Requires-Dist: pandas
Requires-Dist: datasets
